{
  "timestamp": "2025-08-20T23:01:51.030Z",
  "participante": "henriquevalcanaia-swift-vapor",
  "total_liquido": 641190.39855,
  "total_bruto": 1060865.55,
  "total_taxas": 74418.783,
  "descricao": "'total_liquido' é sua pontuação final. Equivale ao seu lucro. Fórmula: total_liquido + (total_liquido * p99.bonus) - (total_liquido * multa.porcentagem)",
  "p99": {
    "valor": "1073.61ms",
    "bonus": "0%",
    "max_requests": "603",
    "descricao": "Fórmula para o bônus: max((11 - p99.valor) * 0.02, 0)"
  },
  "multa": {
    "porcentagem": 0.35,
    "total": 345256.36845,
    "composicao": {
      "num_inconsistencias": 429414,
      "descricao": "Se 'num_inconsistencias' > 0, há multa de 35%."
    }
  },
  "caixa_dois": {
    "detectado": true,
    "descricao": "Se 'lag' for negativo, significa que seu backend registrou mais pagamentos do que solicitado, automaticamente desclassificando sua submissão!"
  },
  "lag": {
    "num_pagamentos_total": 52911,
    "num_pagamentos_solicitados": 51631,
    "lag": -1280,
    "descricao": "Lag é a diferença entre a quantidade de solicitações de pagamentos e o que foi realmente computado pelo backend. Mostra a perda de pagamentos possivelmente por estarem enfileirados."
  },
  "pagamentos_solicitados": {
    "qtd_sucesso": 51631,
    "qtd_falha": 12957,
    "descricao": "'qtd_sucesso' foram requests bem sucedidos para 'POST /payments' e 'qtd_falha' os requests com erro."
  },
  "pagamentos_realizados_default": {
    "total_bruto": 1055592.4,
    "num_pagamentos": 52648,
    "total_taxas": 73891.468,
    "descricao": "Informações do backend sobre solicitações de pagamento para o Payment Processor Default."
  },
  "pagamentos_realizados_fallback": {
    "total_bruto": 5273.15,
    "num_pagamentos": 263,
    "total_taxas": 527.315,
    "descricao": "Informações do backend sobre solicitações de pagamento para o Payment Processor Fallback."
  }
}